src/fir_12bit.v
//15-Apr-2018 11:14:51
`timescale 1ns/1ps

module fir_12bit(
	input clk,
	input rst,
	input wire signed [11:0] signal_in,
	output wire signed [11:0] signal_out
);


reg signed [29:0] unit;
    
reg signed [11:0] delay_pipeline[63:0];

wire signed [15:0] coef[63:0];
// 64 coef begin
    assign coef[0] = 3;
    assign coef[1] = -37;
    assign coef[2] = -33;
    assign coef[3] = -17;
    assign coef[4] = 22;
    assign coef[5] = 64;
    assign coef[6] = 77;
    assign coef[7] = 38;
    assign coef[8] = -46;
    assign coef[9] = -131;
    assign coef[10] = -154;
    assign coef[11] = -74;
    assign coef[12] = 87;
    assign coef[13] = 242;
    assign coef[14] = 279;
    assign coef[15] = 133;
    assign coef[16] = -153;
    assign coef[17] = -421;
    assign coef[18] = -482;
    assign coef[19] = -228;
    assign coef[20] = 262;
    assign coef[21] = 727;
    assign coef[22] = 838;
    assign coef[23] = 403;
    assign coef[24] = -473;
    assign coef[25] = -1357;
    assign coef[26] = -1645;
    assign coef[27] = -850;
    assign coef[28] = 1112;
    assign coef[29] = 3805;
    assign coef[30] = 6394;
    assign coef[31] = 7978;
    assign coef[32] = 7978;
    assign coef[33] = 6394;
    assign coef[34] = 3805;
    assign coef[35] = 1112;
    assign coef[36] = -850;
    assign coef[37] = -1645;
    assign coef[38] = -1357;
    assign coef[39] = -473;
    assign coef[40] = 403;
    assign coef[41] = 838;
    assign coef[42] = 727;
    assign coef[43] = 262;
    assign coef[44] = -228;
    assign coef[45] = -482;
    assign coef[46] = -421;
    assign coef[47] = -153;
    assign coef[48] = 133;
    assign coef[49] = 279;
    assign coef[50] = 242;
    assign coef[51] = 87;
    assign coef[52] = -74;
    assign coef[53] = -154;
    assign coef[54] = -131;
    assign coef[55] = -46;
    assign coef[56] = 38;
    assign coef[57] = 77;
    assign coef[58] = 64;
    assign coef[59] = 22;
    assign coef[60] = -17;
    assign coef[61] = -33;
    assign coef[62] = -37;
    assign coef[63] = 3;
// 64 coef end
   reg signed [29:0] product[63:0];
   
   reg signed [29:0] sum_buf;
   
   reg signed [11:0] data_in_buf;
   
   always @(posedge clk or negedge rst) begin
		if(!rst) begin
			data_in_buf <= 0;
		end
        else begin
		    data_in_buf <= signal_in;
		end
		
	end

    
	always @(posedge clk or negedge rst) begin
		if (!rst) begin
            delay_pipeline[0] <= 0;
	        delay_pipeline[1] <= 0;
			delay_pipeline[2] <= 0;
			delay_pipeline[3] <= 0;
			delay_pipeline[4] <= 0;
			delay_pipeline[5] <= 0;
			delay_pipeline[6] <= 0;
			delay_pipeline[7] <= 0;
			delay_pipeline[8] <= 0;
	        delay_pipeline[9] <= 0;
			delay_pipeline[10] <= 0;
			delay_pipeline[11] <= 0;
			delay_pipeline[12] <= 0;
			delay_pipeline[13] <= 0;
			delay_pipeline[14] <= 0;
			delay_pipeline[15] <= 0;
			delay_pipeline[16] <= 0;
	        delay_pipeline[17] <= 0;
			delay_pipeline[18] <= 0;
			delay_pipeline[19] <= 0;
			delay_pipeline[20] <= 0;
			delay_pipeline[21] <= 0;
			delay_pipeline[22] <= 0;
			delay_pipeline[23] <= 0;
			delay_pipeline[24] <= 0;
	        delay_pipeline[25] <= 0;
			delay_pipeline[26] <= 0;
			delay_pipeline[27] <= 0;
			delay_pipeline[28] <= 0;
			delay_pipeline[29] <= 0;
			delay_pipeline[30] <= 0;
			delay_pipeline[31] <= 0;
			delay_pipeline[32] <= 0;
	        delay_pipeline[33] <= 0;
			delay_pipeline[34] <= 0;
			delay_pipeline[35] <= 0;
			delay_pipeline[36] <= 0;
			delay_pipeline[37] <= 0;
			delay_pipeline[38] <= 0;
			delay_pipeline[39] <= 0;
			delay_pipeline[40] <= 0;
	        delay_pipeline[41] <= 0;
			delay_pipeline[42] <= 0;
			delay_pipeline[43] <= 0;
			delay_pipeline[44] <= 0;
			delay_pipeline[45] <= 0;
			delay_pipeline[46] <= 0;
			delay_pipeline[47] <= 0;
			delay_pipeline[48] <= 0;
	        delay_pipeline[49] <= 0;
			delay_pipeline[50] <= 0;
			delay_pipeline[51] <= 0;
			delay_pipeline[52] <= 0;
			delay_pipeline[53] <= 0;
			delay_pipeline[54] <= 0;
			delay_pipeline[55] <= 0;
			delay_pipeline[56] <= 0;
	        delay_pipeline[57] <= 0;
			delay_pipeline[58] <= 0;
			delay_pipeline[59] <= 0;
			delay_pipeline[60] <= 0;
			delay_pipeline[61] <= 0;
			delay_pipeline[62] <= 0;
			delay_pipeline[63] <= 0;
		end
		else begin
			delay_pipeline[0] <= data_in_buf;
	        delay_pipeline[1] <= delay_pipeline[0] ;
			delay_pipeline[2] <= delay_pipeline[1] ;
			delay_pipeline[3] <= delay_pipeline[2] ;
			delay_pipeline[4] <= delay_pipeline[3] ;
			delay_pipeline[5] <= delay_pipeline[4] ;
			delay_pipeline[6] <= delay_pipeline[5] ;
			delay_pipeline[7] <= delay_pipeline[6] ;
			delay_pipeline[8] <= delay_pipeline[7] ;
	        delay_pipeline[9] <= delay_pipeline[8] ;
			delay_pipeline[10] <=delay_pipeline[9] ;
			delay_pipeline[11] <=delay_pipeline[10];
			delay_pipeline[12] <=delay_pipeline[11];
			delay_pipeline[13] <=delay_pipeline[12];
			delay_pipeline[14] <=delay_pipeline[13];
			delay_pipeline[15] <=delay_pipeline[14];
			delay_pipeline[16] <=delay_pipeline[15];
	        delay_pipeline[17] <=delay_pipeline[16];
			delay_pipeline[18] <=delay_pipeline[17];
			delay_pipeline[19] <=delay_pipeline[18];
			delay_pipeline[20] <=delay_pipeline[19];
			delay_pipeline[21] <=delay_pipeline[20];
			delay_pipeline[22] <=delay_pipeline[21];
			delay_pipeline[23] <=delay_pipeline[22];
			delay_pipeline[24] <=delay_pipeline[23];
	        delay_pipeline[25] <=delay_pipeline[24];
			delay_pipeline[26] <=delay_pipeline[25];
			delay_pipeline[27] <=delay_pipeline[26];
			delay_pipeline[28] <=delay_pipeline[27];
			delay_pipeline[29] <=delay_pipeline[28];
			delay_pipeline[30] <=delay_pipeline[29];
			delay_pipeline[31] <=delay_pipeline[30];
			delay_pipeline[32] <=delay_pipeline[31];
	        delay_pipeline[33] <=delay_pipeline[32];
			delay_pipeline[34] <=delay_pipeline[33];
			delay_pipeline[35] <=delay_pipeline[34];
			delay_pipeline[36] <=delay_pipeline[35];
			delay_pipeline[37] <=delay_pipeline[36];
			delay_pipeline[38] <=delay_pipeline[37];
			delay_pipeline[39] <=delay_pipeline[38];
			delay_pipeline[40] <=delay_pipeline[39];
	        delay_pipeline[41] <=delay_pipeline[40];
			delay_pipeline[42] <=delay_pipeline[41];
			delay_pipeline[43] <=delay_pipeline[42];
			delay_pipeline[44] <=delay_pipeline[43];
			delay_pipeline[45] <=delay_pipeline[44];
			delay_pipeline[46] <=delay_pipeline[45];
			delay_pipeline[47] <=delay_pipeline[46];
			delay_pipeline[48] <=delay_pipeline[47];
	        delay_pipeline[49] <=delay_pipeline[48];
			delay_pipeline[50] <=delay_pipeline[49];
			delay_pipeline[51] <=delay_pipeline[50];
			delay_pipeline[52] <=delay_pipeline[51];
			delay_pipeline[53] <=delay_pipeline[52];
			delay_pipeline[54] <=delay_pipeline[53];
			delay_pipeline[55] <=delay_pipeline[54];
			delay_pipeline[56] <=delay_pipeline[55];
	        delay_pipeline[57] <=delay_pipeline[56];
			delay_pipeline[58] <=delay_pipeline[57];
			delay_pipeline[59] <=delay_pipeline[58];
			delay_pipeline[60] <=delay_pipeline[59];
			delay_pipeline[61] <=delay_pipeline[60];
			delay_pipeline[62] <=delay_pipeline[61];
			delay_pipeline[63] <=delay_pipeline[62];	
		end
	end
	
	always @(posedge clk or negedge rst) begin
		if (!rst) begin
			product[0] <= 0;
			product[1] <= 0;
			product[2] <= 0;
			product[3] <= 0;
			product[4] <= 0;
			product[5] <= 0;
			product[6] <= 0;
			product[7] <= 0;
			product[8] <= 0;
			product[9] <= 0;
			product[10] <= 0;
			product[11] <= 0;
			product[12] <= 0;
			product[13] <= 0;
			product[14] <= 0;
			product[15] <= 0;
			product[16] <= 0;
			product[17] <= 0;
			product[18] <= 0;
			product[19] <= 0;
			product[20] <= 0;
			product[21] <= 0;
			product[22] <= 0;
			product[23] <= 0;
			product[24] <= 0;
			product[25] <= 0;
			product[26] <= 0;
			product[27] <= 0;
			product[28] <= 0;
			product[29] <= 0;
			product[30] <= 0;
			product[31] <= 0;
			product[32] <= 0;
			product[33] <= 0;
			product[34] <= 0;
			product[35] <= 0;
			product[36] <= 0;
			product[37] <= 0;
			product[38] <= 0;
			product[39] <= 0;
			product[40] <= 0;
			product[41] <= 0;
			product[42] <= 0;
			product[43] <= 0;
			product[44] <= 0;
			product[45] <= 0;
			product[46] <= 0;
			product[47] <= 0;
			product[48] <= 0;
			product[49] <= 0;
			product[50] <= 0;
			product[51] <= 0;
			product[52] <= 0;
			product[53] <= 0;
			product[54] <= 0;
			product[55] <= 0;
			product[56] <= 0;
			product[57] <= 0;
			product[58] <= 0;
			product[59] <= 0;
			product[60] <= 0;
			product[61] <= 0;
			product[62] <= 0;
			product[63] <= 0;
		end
		else begin
			product[0] <=  coef[0]* delay_pipeline[0] ;
		    product[1] <=  coef[1]* delay_pipeline[1] ;
            product[2] <=  coef[2]* delay_pipeline[2] ;
            product[3] <=  coef[3]* delay_pipeline[3] ;
            product[4] <=  coef[4]* delay_pipeline[4] ;
            product[5] <=  coef[5]* delay_pipeline[5] ;
            product[6] <=  coef[6]* delay_pipeline[6] ;
            product[7] <=  coef[7]* delay_pipeline[7] ;
            product[8] <=  coef[8]* delay_pipeline[8] ;
            product[9] <=  coef[9]* delay_pipeline[9] ;
            product[10] <= coef[10]*delay_pipeline[10]; 
            product[11] <= coef[11]*delay_pipeline[11]; 
            product[12] <= coef[12]*delay_pipeline[12];
            product[13] <= coef[13]*delay_pipeline[13];
            product[14] <= coef[14]*delay_pipeline[14];
            product[15] <= coef[15]*delay_pipeline[15];
            product[16] <= coef[16]*delay_pipeline[16];
            product[17] <= coef[17]*delay_pipeline[17];
            product[18] <= coef[18]*delay_pipeline[18];
            product[19] <= coef[19]*delay_pipeline[19];
            product[20] <= coef[20]*delay_pipeline[20];
            product[21] <= coef[21]*delay_pipeline[21];
            product[22] <= coef[22]*delay_pipeline[22];
            product[23] <= coef[23]*delay_pipeline[23];
            product[24] <= coef[24]*delay_pipeline[24];
            product[25] <= coef[25]*delay_pipeline[25];
            product[26] <= coef[26]*delay_pipeline[26];
            product[27] <= coef[27]*delay_pipeline[27];
            product[28] <= coef[28]*delay_pipeline[28];
            product[29] <= coef[29]*delay_pipeline[29];
            product[30] <= coef[30]*delay_pipeline[30];
            product[31] <= coef[31]*delay_pipeline[31];
            product[32] <= coef[32]*delay_pipeline[32];
            product[33] <= coef[33]*delay_pipeline[33];
            product[34] <= coef[34]*delay_pipeline[34];
            product[35] <= coef[35]*delay_pipeline[35];
            product[36] <= coef[36]*delay_pipeline[36];
            product[37] <= coef[37]*delay_pipeline[37];
            product[38] <= coef[38]*delay_pipeline[38];
            product[39] <= coef[39]*delay_pipeline[39];
            product[40] <= coef[40]*delay_pipeline[40];
            product[41] <= coef[41]*delay_pipeline[41];
            product[42] <= coef[42]*delay_pipeline[42];
            product[43] <= coef[43]*delay_pipeline[43];
            product[44] <= coef[44]*delay_pipeline[44];
            product[45] <= coef[45]*delay_pipeline[45];
            product[46] <= coef[46]*delay_pipeline[46];
            product[47] <= coef[47]*delay_pipeline[47];
            product[48] <= coef[48]*delay_pipeline[48];
            product[49] <= coef[49]*delay_pipeline[49];
            product[50] <= coef[50]*delay_pipeline[50];
            product[51] <= coef[51]*delay_pipeline[51];
            product[52] <= coef[52]*delay_pipeline[52];
            product[53] <= coef[53]*delay_pipeline[53];
            product[54] <= coef[54]*delay_pipeline[54];
            product[55] <= coef[55]*delay_pipeline[55];
            product[56] <= coef[56]*delay_pipeline[56];
            product[57] <= coef[57]*delay_pipeline[57];
            product[58] <= coef[58]*delay_pipeline[58];
            product[59] <= coef[59]*delay_pipeline[59];
            product[60] <= coef[60]*delay_pipeline[60];
            product[61] <= coef[61]*delay_pipeline[61];
            product[62] <= coef[62]*delay_pipeline[62];
            product[63] <= coef[63]*delay_pipeline[63];
		end
	end
    
    always @(posedge clk or negedge rst) begin
		if (!rst) begin
			sum_buf <= 0;
		end
		else begin
			sum_buf <= product[0]+ product[1]+ product[2]+ product[3]
			+product[4]+product[5]+product[6]+product[7]
			+product[8]+product[9]+product[10]+product[11]
			+product[12]+product[13]+product[14]+product[15]
			+product[16]+product[17]+product[18]+product[19]
			+product[20]+product[21]+product[22]+product[23]
			+product[24]+product[25]+product[26]+product[27]
			+product[28]+product[29]+product[30]+product[31]
			+product[32]+product[33]+product[34]+product[35]
			+product[36]+product[37]+product[38]+product[39]
			+product[40]+product[41]+product[42]+product[43]
			+product[44]+product[45]+product[46]+product[47]
			+product[48]+product[49]+product[50]+product[51]
			+product[52]+product[53]+product[54]+product[55]
			+product[56]+product[57]+product[58]+product[59]
			+product[60]+product[61]+product[62]+product[63];
		end
	end	
	
	always @(sum_buf) begin
		if (!rst) begin
			unit <= 0;
		end
		else begin
		    unit <= (sum_buf >> 15);
		end
	end
	
	assign signal_out = unit[11:0];
	
endmodule

sim/tb_fir.v
`timescale 1ns/1ns
module tb_fir;

	reg clk;
	reg rst;
	reg signed [11:0] signal_in;
	wire signed [11:0] signal_out;
	
	fir_12bit dut (
		.clk(clk),
		.rst(rst),
		.signal_in(signal_in),
		.signal_out(signal_out)
	);
	
	initial begin
	
		$dumpfile("vsim.vcd");
		$dumpvars();
		$dumpvars(1,tb_fir.dut);
		
		
		#100000
		$finish;
	end
	
	initial begin
	
		rst = 0;
		#15
		rst = 1;
		
	end
	
	initial begin
	
		clk = 0;
		forever #10 clk = ~clk;//50MHz
	
	end
	
	reg signed[11:0] mem[1600:0];
	
	initial begin
	
		$readmemb("signal_in.txt",mem);
	 
	end
	
	integer i = 0;
	
	initial begin
		#11;
		for(i=0;i<1601;i++) begin
		
			signal_in = mem[i];
		    #20;
		end
    end
	
	// always@(posedge clk) begin
	
		 // signal_out <= signal_in;
	
	// end
	
	//write data to txt file
	integer file;
	integer cnt = 0;
	
	initial begin
	    #33
		file = $fopen("dataout.txt","w");
	end
	
	always @(posedge clk) begin
		$fdisplay(file,signal_out);
		cnt <= cnt + 1;
		if(cnt == 1602) begin
			$fclose(file);
		end
	end
	
endmodule

sim/vsim.vcd
$date
	Sun Apr 15 11:14:59 2018
$end
$version
	Icarus Verilog
$end
$timescale
	1ps
$end
$scope module tb_fir $end
$var wire 12 ! signal_out [11:0] $end
$var reg 1 " clk $end
$var reg 1 # rst $end
$var reg 12 $ signal_in [11:0] $end
$var integer 32 % cnt [31:0] $end
$var integer 32 & file [31:0] $end
$var integer 32 ' i [31:0] $end
$scope module dut $end
$var wire 1 " clk $end
$var wire 1 # rst $end
$var wire 12 ( signal_in [11:0] $end
$var wire 12 ) signal_out [11:0] $end
$var reg 12 * data_in_buf [11:0] $end
$var reg 30 + sum_buf [29:0] $end
$var reg 30 , unit [29:0] $end
$upscope $end
$upscope $end
$scope module tb_fir $end
$scope module dut $end
$upscope $end
$upscope $end
$enddefinitions $end
#0
$dumpvars
b0 ,
b0 +
b0 *
b0 )
bx (
b0 '
bx &
b0 %
bx $
0#
0"
b0 !
$end
#10000
b1 %
1"
#11000
b10100000 $
b10100000 (
#15000
1#
#20000
0"
#30000
b10100000 *
b10 %
1"
#31000
b100111100 $
b100111100 (
b1 '
#33000
b10000000000000000000000000000011 &
#40000
0"
#50000
b100111100 *
b11 %
1"
#51000
b111010001 $
b111010001 (
b10 '
#60000
0"
#70000
b111010001 *
b100 %
1"
#71000
b1001011010 $
b1001011010 (
b11 '
#80000
0"
#90000
b111100000 +
b1001011010 *
b101 %
1"
#91000
b1011010100 $
b1011010100 (
b100 '
#100000
0"
#110000
b111111111111 !
b111111111111 )
b111111111111111 ,
b1011010100 *
b111111111111111110110010010100 +
b110 %
1"
#111000
b1100111100 $
b1100111100 (
b101 '
#120000
0"
#130000
b111111111111111100001100100111 +
b1100111100 *
b111 %
1"
#131000
b1110010000 $
b1110010000 (
b110 '
#140000
0"
#150000
b1110010000 *
b111111111111111001000001111101 +
b1000 %
1"
#151000
b1111001101 $
b1111001101 (
b111 '
#160000
0"
#170000
b111111111110 !
b111111111110 )
b111111111111110 ,
b111111111111110110111001001101 +
b1111001101 *
b1001 %
1"
#171000
b1111110011 $
b1111110011 (
b1000 '
#180000
0"
#190000
b1111110011 *
b111111111111110111011110111101 +
b1010 %
1"
#191000
b10000000000 $
b10000000000 (
b1001 '
#200000
0"
#210000
b111111111111 !
b111111111111 )
b111111111111111 ,
b111111111111111011010011001100 +
b10000000000 *
b1011 %
1"
#211000
b1111110011 $
b1111110011 (
b1010 '
#220000
0"
#230000
b0 !
b0 )
b0 ,
b1111110011 *
b101110001111 +
b1100 %
1"
#231000
b1111001101 $
b1111001101 (
b1011 '
#240000
0"
#250000
b100010101101001 +
b1111001101 *
b1101 %
1"
#251000
b1110010000 $
b1110010000 (
b1100 '
#260000
0"
#270000
b1110010000 *
b10101101111100 +
b1110 %
1"
#271000
b1100111100 $
b1100111100 (
b1101 '
#280000
0"
#290000
b111111111111 !
b111111111111 )
b111111111111111 ,
b111111111111111010111111100111 +
b1100111100 *
b1111 %
1"
#291000
b1011010100 $
b1011010100 (
b1110 '
#300000
0"
#310000
b111111111110 !
b111111111110 )
b111111111111110 ,
b1011010100 *
b111111111111110000011111010000 +
b10000 %
1"
#311000
b1001011010 $
b1001011010 (
b1111 '
#320000
0"
#330000
b111111111101 !
b111111111101 )
b111111111111101 ,
b111111111111101001110000111110 +
b1001011010 *
b10001 %
1"
#331000
b111010001 $
b111010001 (
b10000 '
#340000
0"
#350000
b111010001 *
b111111111111101101000011101111 +
b10010 %
1"
#351000
b100111100 $
b100111100 (
b10001 '
#360000
0"
#370000
b111111111111 !
b111111111111 )
b111111111111111 ,
b111111111111111011110000001001 +
b100111100 *
b10011 %
1"
#371000
b10100000 $
b10100000 (
b10010 '
#380000
0"
#390000
b1 !
b1 )
b1 ,
b10100000 *
b1111110001010100 +
b10100 %
1"
#391000
b0 $
b0 (
b10011 '
#400000
0"
#410000
b11 !
b11 )
b11 ,
b11101011011000010 +
b0 *
b10101 %
1"
#411000
b111101100000 $
b111101100000 (
b10100 '
#420000
0"
#430000
b111101100000 *
b11001110111100100 +
b10110 %
1"
#431000
b111011000100 $
b111011000100 (
b10101 '
#440000
0"
#450000
b0 !
b0 )
b0 ,
b10110011000110 +
b111011000100 *
b10111 %
1"
#451000
b111000101111 $
b111000101111 (
b10110 '
#460000
0"
#470000
b111111111100 !
b111111111100 )
b111111111111100 ,
b111000101111 *
b111111111111100010101101011010 +
b11000 %
1"
#471000
b110110100110 $
b110110100110 (
b10111 '
#480000
0"
#490000
b111111111001 !
b111111111001 )
b111111111111001 ,
b111111111111001101100101000100 +
b110110100110 *
b11001 %
1"
#491000
b110100101100 $
b110100101100 (
b11000 '
#500000
0"
#510000
b111111111010 !
b111111111010 )
b111111111111010 ,
b110100101100 *
b111111111111010110001001010111 +
b11010 %
1"
#511000
b110011000100 $
b110011000100 (
b11001 '
#520000
0"
#530000
b0 !
b0 )
b0 ,
b100100001101 +
b110011000100 *
b11011 %
1"
#531000
b110001110000 $
b110001110000 (
b11010 '
#540000
0"
#550000
b111 !
b111 )
b111 ,
b110001110000 *
b111010110010100011 +
b11100 %
1"
#551000
b110000110011 $
b110000110011 (
b11011 '
#560000
0"
#570000
b1100 !
b1100 )
b1100 ,
b1100001000101101010 +
b110000110011 *
b11101 %
1"
#571000
b110000001101 $
b110000001101 (
b11100 '
#580000
0"
#590000
b1001 !
b1001 )
b1001 ,
b110000001101 *
b1001111111001001000 +
b11110 %
1"
#591000
b110000000000 $
b110000000000 (
b11101 '
#600000
0"
#610000
b111111111111 !
b111111111111 )
b111111111111111 ,
b111111111111111100010011110111 +
b110000000000 *
b11111 %
1"
#611000
b110000001101 $
b110000001101 (
b11110 '
#620000
0"
#630000
b111111110000 !
b111111110000 )
b111111111110000 ,
b110000001101 *
b111111111110000111011110100000 +
b100000 %
1"
#631000
b110000110011 $
b110000110011 (
b11111 '
#640000
0"
#650000
b111111101000 !
b111111101000 )
b111111111101000 ,
b111111111101000001000001010001 +
b110000110011 *
b100001 %
1"
#651000
b110001110000 $
b110001110000 (
b100000 '
#660000
0"
#670000
b111111110010 !
b111111110010 )
b111111111110010 ,
b110001110000 *
b111111111110010100000100010001 +
b100010 %
1"
#671000
b110011000100 $
b110011000100 (
b100001 '
#680000
0"
#690000
b11100 !
b11100 )
b11100 ,
b11100011111000110001 +
b110011000100 *
b100011 %
1"
#691000
b110100101100 $
b110100101100 (
b100010 '
#700000
0"
#710000
b1101100 !
b1101100 )
b1101100 ,
b110100101100 *
b1101100110001011011011 +
b100100 %
1"
#711000
b110110100110 $
b110110100110 (
b100011 '
#720000
0"
#730000
b11100001 !
b11100001 )
b11100001 ,
b11100001011000101100000 +
b110110100110 *
b100101 %
1"
#731000
b111000101111 $
b111000101111 (
b100100 '
#740000
0"
#750000
b101101111 !
b101101111 )
b101101111 ,
b111000101111 *
b101101111101100110110101 +
b100110 %
1"
#751000
b111011000100 $
b111011000100 (
b100101 '
#760000
0"
#770000
b1000000111 !
b1000000111 )
b1000000111 ,
b1000000111100010101110010 +
b111011000100 *
b100111 %
1"
#771000
b111101100000 $
b111101100000 (
b100110 '
#780000
0"
#790000
b1010010111 !
b1010010111 )
b1010010111 ,
b111101100000 *
b1010010111111111111010000 +
b101000 %
1"
#791000
b0 $
b0 (
b100111 '
#800000
0"
#810000
b1100010011 !
b1100010011 )
b1100010011 ,
b1100010011111010110111000 +
b0 *
b101001 %
1"
#811000
b10100000 $
b10100000 (
b101000 '
#820000
0"
#830000
b1101110100 !
b1101110100 )
b1101110100 ,
b10100000 *
b1101110100011000001000011 +
b101010 %
1"
#831000
b100111100 $
b100111100 (
b101001 '
#840000
0"
#850000
b1110111000 !
b1110111000 )
b1110111000 ,
b1110111000011010101111110 +
b100111100 *
b101011 %
1"
#851000
b111010001 $
b111010001 (
b101010 '
#860000
0"
#870000
b1111100010 !
b1111100010 )
b1111100010 ,
b111010001 *
b1111100010101101001000101 +
b101100 %
1"
#871000
b1001011010 $
b1001011010 (
b101011 '
#880000
0"
#890000
b1111110110 !
b1111110110 )
b1111110110 ,
b1111110110011111011101101 +
b1001011010 *
b101101 %
1"
#891000
b1011010100 $
b1011010100 (
b101100 '
#900000
0"
#910000
b1111110101 !
b1111110101 )
b1111110101 ,
b1011010100 *
b1111110101011010111011010 +
b101110 %
1"
#911000
b1100111100 $
b1100111100 (
b101101 '
#920000
0"
#930000
b1111011110 !
b1111011110 )
b1111011110 ,
b1111011110111110010010010 +
b1100111100 *
b101111 %
1"
#931000
b1110010000 $
b1110010000 (
b101110 '
#940000
0"
#950000
b1110110001 !
b1110110001 )
b1110110001 ,
b1110010000 *
b1110110001011010110100001 +
b110000 %
1"
#951000
b1111001101 $
b1111001101 (
b101111 '
#960000
0"
#970000
b1101101011 !
b1101101011 )
b1101101011 ,
b1101101011011110010111101 +
b1111001101 *
b110001 %
1"
#971000
b1111110011 $
b1111110011 (
b110000 '
#980000
0"
#990000
b1100001101 !
b1100001101 )
b1100001101 ,
b1111110011 *
b1100001101100111000110010 +
b110010 %
1"
#991000
b10000000000 $
b10000000000 (
b110001 '
#1000000
0"
#1010000
b1010011010 !
b1010011010 )
b1010011010 ,
b1010011010011011100101101 +
b10000000000 *
b110011 %
1"
#1011000
b1111110011 $
b1111110011 (
b110010 '
#1020000
0"
#1030000
b1000010110 !
b1000010110 )
b1000010110 ,
b1111110011 *
b1000010110000100111011011 +
b110100 %
1"
#1031000
b1111001101 $
b1111001101 (
b110011 '
#1040000
0"
#1050000
b110000101 !
b110000101 )
b110000101 ,
b110000101001101001010011 +
b1111001101 *
b110101 %
1"
#1051000
b1110010000 $
b1110010000 (
b110100 '
#1060000
0"
#1070000
b11101100 !
b11101100 )
b11101100 ,
b1110010000 *
b11101100000110010001101 +
b110110 %
1"
#1071000
b1100111100 $
b1100111100 (
b110101 '
#1080000
0"
#1090000
b1001110 !
b1001110 )
b1001110 ,
b1001110010110001111010 +
b1100111100 *
b110111 %
1"
#1091000
b1011010100 $
b1011010100 (
b110110 '
#1100000
0"
#1110000
b111110101111 !
b111110101111 )
b111111110101111 ,
b1011010100 *
b111111110101111000101100111101 +
b111000 %
1"
#1111000
b1001011010 $
b1001011010 (
b110111 '
#1120000
0"
#1130000
b111100010001 !
b111100010001 )
b111111100010001 ,
b111111100010001011101100101101 +
b1001011010 *
b111001 %
1"
#1131000
b111010001 $
b111010001 (
b111000 '
#1140000
0"
#1150000
b111001111000 !
b111001111000 )
b111111001111000 ,
b111010001 *
b111111001111000111110000000101 +
b111010 %
1"
#1151000
b100111100 $
b100111100 (
b111001 '
#1160000
0"
#1170000
b110111101001 !
b110111101001 )
b111110111101001 ,
b111110111101001011110110111101 +
b100111100 *
b111011 %
1"
#1171000
b10100000 $
b10100000 (
b111010 '
#1180000
0"
#1190000
b110101100110 !
b110101100110 )
b111110101100110 ,
b10100000 *
b111110101100110111100111110011 +
b111100 %
1"
#1191000
b0 $
b0 (
b111011 '
#1200000
0"
#1210000
b110011110101 !
b110011110101 )
b111110011110101 ,
b111110011110101000000001001101 +
b0 *
b111101 %
1"
#1211000
b111101100000 $
b111101100000 (
b111100 '
#1220000
0"
#1230000
b110010010110 !
b110010010110 )
b111110010010110 ,
b111101100000 *
b111110010010110100111101110100 +
b111110 %
1"
#1231000
b111011000100 $
b111011000100 (
b111101 '
#1240000
0"
#1250000
b110001001110 !
b110001001110 )
b111110001001110 ,
b111110001001110000011110100010 +
b111011000100 *
b111111 %
1"
#1251000
b111000101111 $
b111000101111 (
b111110 '
#1260000
0"
#1270000
b110000011100 !
b110000011100 )
b111110000011100 ,
b111000101111 *
b111110000011100111000111101111 +
b1000000 %
1"
#1271000
b110110100110 $
b110110100110 (
b111111 '
#1280000
0"
#1290000
b110000000100 !
b110000000100 )
b111110000000100 ,
b111110000000100000111111111110 +
b110110100110 *
b1000001 %
1"
#1291000
b110100101100 $
b110100101100 (
b1000000 '
#1300000
0"
#1310000
b110100101100 *
b111110000000100010010101001010 +
b1000010 %
1"
#1311000
b110011000100 $
b110011000100 (
b1000001 '
#1320000
0"
#1330000
b110000011101 !
b110000011101 )
b111110000011101 ,
b111110000011101010111011001000 +
b110011000100 *
b1000011 %
1"
#1331000
b110001110000 $
b110001110000 (
b1000010 '
#1340000
0"
#1350000
b110001001110 !
b110001001110 )
b111110001001110 ,
b110001110000 *
b111110001001110111011100100101 +
b1000100 %
1"
#1351000
b110000110011 $
b110000110011 (
b1000011 '
#1360000
0"
#1370000
b110010010111 !
b110010010111 )
b111110010010111 ,
b111110010010111110000100100111 +
b110000110011 *
b1000101 %
1"
#1371000
b110000001101 $
b110000001101 (
b1000100 '
#1380000
0"
#1390000
b110011110110 !
b110011110110 )
b111110011110110 ,
b110000001101 *
b111110011110110000100010010000 +
b1000110 %
1"
#1391000
b110000000000 $
b110000000000 (
b1000101 '
#1400000
0"
#1410000
b110101100111 !
b110101100111 )
b111110101100111 ,
b111110101100111100010100100111 +
b110000000000 *
b1000111 %
1"
#1411000
b110000001101 $
b110000001101 (
b1000110 '
#1420000
0"
#1430000
b110111101001 !
b110111101001 )
b111110111101001 ,
b110000001101 *
b111110111101001011001000101110 +
b1001000 %
1"
#1431000
b110000110011 $
b110000110011 (
b1000111 '
#1440000
0"
#1450000
b111001111000 !
b111001111000 )
b111111001111000 ,
b111111001111000011011010011100 +
b110000110011 *
b1001001 %
1"
#1451000
b110001110000 $
b110001110000 (
b1001000 '
#1460000
0"
#1470000
b111100010001 !
b111100010001 )
b111111100010001 ,
b110001110000 *
b111111100010001000111110110001 +
b1001010 %
1"
#1471000
b110011000100 $
b110011000100 (
b1001001 '
#1480000
0"
#1490000
b111110101111 !
b111110101111 )
b111111110101111 ,
b111111110101111101101101010110 +
b110011000100 *
b1001011 %
1"
#1491000
b110100101100 $
b110100101100 (
b1001010 '
#1500000
0"
#1510000
b1010000 !
b1010000 )
b1010000 ,
b110100101100 *
b1010000010010010101010 +
b1001100 %
1"
#1511000
b110110100110 $
b110110100110 (
b1001011 '
#1520000
0"
#1530000
b11101110 !
b11101110 )
b11101110 ,
b11101110111000001001111 +
b110110100110 *
b1001101 %
1"
#1531000
b111000101111 $
b111000101111 (
b1001100 '
#1540000
0"
#1550000
b110000111 !
b110000111 )
b110000111 ,
b111000101111 *
b110000111100100101100100 +
b1001110 %
1"
#1551000
b111011000100 $
b111011000100 (
b1001101 '
#1560000
0"
#1570000
b1000010110 !
b1000010110 )
b1000010110 ,
b1000010110100110111010010 +
b111011000100 *
b1001111 %
1"
#1571000
b111101100000 $
b111101100000 (
b1001110 '
#1580000
0"
#1590000
b1010011000 !
b1010011000 )
b1010011000 ,
b111101100000 *
b1010011000011101011011001 +
b1010000 %
1"
#1591000
b0 $
b0 (
b1001111 '
#1600000
0"
#1610000
b1100001001 !
b1100001001 )
b1100001001 ,
b1100001001111011101110000 +
b0 *
b1010001 %
1"
#1611000
b10100000 $
b10100000 (
b1010000 '
#1620000
0"
#1630000
b1101101000 !
b1101101000 )
b1101101000 ,
b10100000 *
b1101101000001111011011001 +
b1010010 %
1"
#1631000
b100111100 $
b100111100 (
b1010001 '
#1640000
0"
#1650000
b1110110001 !
b1110110001 )
b1110110001 ,
b1110110001000100011011011 +
b100111100 *
b1010011 %
1"
#1651000
b111010001 $
b111010001 (
b1010010 '
#1660000
0"
